{"cameraMode":{"drawMode":0,"name":"Shaded","section":"Shading Mode"},"sceneLighting":true,"audioPlay":false,"sceneViewState":{"showFog":true,"showMaterialUpdate":false,"showSkybox":true,"showFlares":true,"showImageEffects":true,"showParticleSystems":true},"in2DMode":false,"pivot":{"x":710.053466796875,"y":-38.93021774291992,"z":254.77081298828126},"rotation":{"x":-0.036587364971637729,"y":-0.7441169023513794,"z":0.04089203476905823,"w":-0.6657941937446594},"size":393.271728515625,"orthographic":false}